README.md
setup.py
roblox_aio/__init__.py
roblox_aio/auth.py
roblox_aio/endpoints.py
roblox_aio/errors.py
roblox_aio/user.py
roblox_aio.py.egg-info/PKG-INFO
roblox_aio.py.egg-info/SOURCES.txt
roblox_aio.py.egg-info/dependency_links.txt
roblox_aio.py.egg-info/requires.txt
roblox_aio.py.egg-info/top_level.txt