Metadata-Version: 2.1
Name: roblox-aio.py
Version: 1.0.7
Summary: A Roblox API wrapper used for getting data from Roblox API.
Home-page: https://github.com/RainzDev/roblox-aio.py
Author: RainzDev
Author-email: jessrblx16@gmail.com
License: MIT
Platform: UNKNOWN
